MANIFEST.in
README.rst
setup.py
collective/__init__.py
collective.geo.fastkml.egg-info/PKG-INFO
collective.geo.fastkml.egg-info/SOURCES.txt
collective.geo.fastkml.egg-info/dependency_links.txt
collective.geo.fastkml.egg-info/entry_points.txt
collective.geo.fastkml.egg-info/namespace_packages.txt
collective.geo.fastkml.egg-info/not-zip-safe
collective.geo.fastkml.egg-info/requires.txt
collective.geo.fastkml.egg-info/top_level.txt
collective/geo/__init__.py
collective/geo/fastkml/__init__.py
collective/geo/fastkml/configure.zcml
collective/geo/fastkml/interfaces.py
collective/geo/fastkml/profiles.zcml
collective/geo/fastkml/tests.py
collective/geo/fastkml/version.txt
collective/geo/fastkml/browser/__init__.py
collective/geo/fastkml/browser/configure.zcml
collective/geo/fastkml/browser/kmldocument.py
collective/geo/fastkml/locales/collective.geo.fastkml.pot
collective/geo/fastkml/locales/rebuild.sh
collective/geo/fastkml/locales/nl/LC_MESSAGES/collective.geo.fastkml.po
collective/geo/fastkml/profiles/default/browserlayer.xml
collective/geo/fastkml/profiles/default/metadata.xml
docs/HISTORY.txt
docs/INSTALL.txt
docs/LICENSE.txt