Metadata-Version: 1.1
Name: collective.geo.fastkml
Version: 0.3
Summary: Generate KML with fastkml for collective.geo
Home-page: https://github.com/collective/collective.geo.fastkml
Author: Christian Ledermann
Author-email: christian.ledermann@gmail.com
License: GPL
Platform: UNKNOWN
Classifier: Framework :: Plone
Classifier: Framework :: Plone :: 4.0
Classifier: Framework :: Plone :: 4.1
Classifier: Programming Language :: Python
Classifier: Topic :: Scientific/Engineering :: GIS
Classifier: License :: OSI Approved :: GNU General Public License (GPL)
Classifier: Development Status :: 4 - Beta
Classifier: Operating System :: OS Independent
